django_import_file/__init__.py
django_import_file/import_file.py
django_import_file-0.0.6.dist-info/LICENSE
django_import_file-0.0.6.dist-info/METADATA
django_import_file-0.0.6.dist-info/WHEEL
django_import_file-0.0.6.dist-info/top_level.txt
django_import_file-0.0.6.dist-info/RECORD
