Metadata-Version: 2.1
Name: django_import_file
Version: 0.0.6
Summary: Django Mixin allows easy import of files into Django models.
Author: Jakub Jadczak
Author-email: <jakubjadczak02@gmail.com>
Keywords: python,django,import,file,import file,import excel
Classifier: Development Status :: 2 - Pre-Alpha
Classifier: Intended Audience :: Developers
Classifier: Framework :: Django :: 5.1
Classifier: Programming Language :: Python :: 3
Classifier: Operating System :: OS Independent
License-File: LICENSE
Requires-Dist: pandas
Requires-Dist: openpyxl
